simple_apns/__init__.py
simple_apns/auth.py
simple_apns/client.py
simple_apns/exceptions.py
simple_apns/payload.py
simple_apns/django/__init__.py
simple_apns/django/apps.py
simple_apns/django/integration.py
tests/__init__.py
tests/conftest.py
tests/test_auth.py
tests/test_client.py
tests/test_django_integration.py
tests/test_exceptions.py
tests/test_payload.py
simple_apns-0.1.2.dist-info/LICENSE
simple_apns-0.1.2.dist-info/METADATA
simple_apns-0.1.2.dist-info/WHEEL
simple_apns-0.1.2.dist-info/top_level.txt
simple_apns-0.1.2.dist-info/RECORD
