Metadata-Version: 2.2
Name: simple-apns
Version: 0.1.2
Summary: Synchronous Python client for Apple Push Notification Service
Home-page: https://github.com/netshy/simple-apns
Author: Ivan Lundak
Author-email: n3tshy@gmail.com
Keywords: apns,push,notifications,apple,ios,django
Classifier: Development Status :: 4 - Beta
Classifier: Intended Audience :: Developers
Classifier: License :: OSI Approved :: MIT License
Classifier: Programming Language :: Python :: 3.10
Classifier: Programming Language :: Python :: 3.11
Classifier: Programming Language :: Python :: 3.12
Classifier: Programming Language :: Python :: 3.13
Classifier: Topic :: Software Development :: Libraries :: Python Modules
Classifier: Topic :: Communications
Requires-Python: >=3.10
License-File: LICENSE
Requires-Dist: httpx[http2]>=0.20.0
Requires-Dist: PyJWT>=2.0.0
Requires-Dist: cryptography>=3.4.0
Provides-Extra: django
Requires-Dist: Django>=2.2; extra == "django"
Provides-Extra: dev
Requires-Dist: pytest>=6.0.0; extra == "dev"
Requires-Dist: pytest-cov>=2.10.0; extra == "dev"
Requires-Dist: black>=21.5b2; extra == "dev"
Requires-Dist: isort>=5.9.1; extra == "dev"
Requires-Dist: flake8>=3.9.2; extra == "dev"
Requires-Dist: mypy>=0.901; extra == "dev"
Requires-Dist: django>=2.2; extra == "dev"
Dynamic: author
Dynamic: author-email
Dynamic: classifier
Dynamic: description
Dynamic: description-content-type
Dynamic: home-page
Dynamic: keywords
Dynamic: provides-extra
Dynamic: requires-dist
Dynamic: requires-python
Dynamic: summary
